posthog_otel_exporter/__init__.py
posthog_otel_exporter/errors.py
posthog_otel_exporter/exporter.py
posthog_otel_exporter-0.1.0.dist-info/METADATA
posthog_otel_exporter-0.1.0.dist-info/WHEEL
posthog_otel_exporter-0.1.0.dist-info/licenses/LICENSE
posthog_otel_exporter-0.1.0.dist-info/RECORD
