Metadata-Version: 2.4
Name: posthog-otel-exporter
Version: 0.1.0
Summary: Export OpenTelemetry-compatible events to PostHog.
License-File: LICENSE
Requires-Python: >=3.10
Requires-Dist: opentelemetry-sdk>=1.38.0
Requires-Dist: posthog>=7.0.1
